json_fingerprint/__init__.py
json_fingerprint/_create.py
json_fingerprint/_decode.py
json_fingerprint/_find_matches.py
json_fingerprint/_jfpv1.py
json_fingerprint/_load_json.py
json_fingerprint/_match.py
json_fingerprint/_validators.py
json_fingerprint/exceptions.py
json_fingerprint/hash_functions.py
json_fingerprint/tests/__init__.py
json_fingerprint/tests/run.py
json_fingerprint/tests/test_create.py
json_fingerprint/tests/test_decode.py
json_fingerprint/tests/test_find_matches.py
json_fingerprint/tests/test_hash_functions.py
json_fingerprint/tests/test_jfpv1.py
json_fingerprint/tests/test_match.py
json_fingerprint/tests/test_validators.py
json_fingerprint/tests/testdata/jfpv1_test_obj_1.json
json_fingerprint/tests/testdata/jfpv1_test_obj_2.json
json_fingerprint-0.14.1.dist-info/licenses/LICENSE
json_fingerprint-0.14.1.dist-info/METADATA
json_fingerprint-0.14.1.dist-info/WHEEL
json_fingerprint-0.14.1.dist-info/top_level.txt
json_fingerprint-0.14.1.dist-info/RECORD
