Metadata-Version: 2.4
Name: json-fingerprint
Version: 0.14.1
Summary: Create consistent and comparable fingerprints with secure hashes from unordered JSON data
Home-page: https://github.com/cobaltine/json-fingerprint
Author: Ville Lehtinen
Author-email: ville.lehtinen@cobaltine.fi
License: MIT
Project-URL: Changelog, https://github.com/cobaltine/json-fingerprint/releases
Project-URL: Homepage, https://github.com/cobaltine/json-fingerprint
Project-URL: Source, https://github.com/cobaltine/json-fingerprint
Project-URL: Tracker, https://github.com/cobaltine/json-fingerprint/issues
Keywords: json fingerprint hash
Classifier: License :: OSI Approved :: MIT License
Classifier: Development Status :: 4 - Beta
Classifier: Topic :: File Formats :: JSON
Classifier: Operating System :: OS Independent
Classifier: Programming Language :: Python :: 3
Classifier: Programming Language :: Python :: 3.8
Classifier: Programming Language :: Python :: 3.9
Classifier: Programming Language :: Python :: 3.10
Classifier: Programming Language :: Python :: 3.11
Classifier: Programming Language :: Python :: 3.12
Classifier: Programming Language :: Python :: 3.13
Requires-Python: >=3.8
License-File: LICENSE
Dynamic: author
Dynamic: author-email
Dynamic: classifier
Dynamic: description
Dynamic: description-content-type
Dynamic: home-page
Dynamic: keywords
Dynamic: license
Dynamic: license-file
Dynamic: project-url
Dynamic: requires-python
Dynamic: summary
